Metadata-Version: 1.0
Name: fluffy-happiness
Version: 1.0.0
Summary: Deployment example package
Home-page: UNKNOWN
Author: James Collins
Author-email: collijk@uw.edu
License: UNKNOWN
Platform: UNKNOWN
